bitrix24/__init__.py
bitrix24/bitrix24.py
bitrix24/exceptions.py
tests/__init__.py
tests/conftest.py
tests/test_async_call_method.py
tests/test_bitrix24.py
tests/test_pagination.py
tests/test_params_preparation.py
tests/test_request_retry.py
bitrix24_rest-2.0.3.dist-info/LICENSE
bitrix24_rest-2.0.3.dist-info/METADATA
bitrix24_rest-2.0.3.dist-info/WHEEL
bitrix24_rest-2.0.3.dist-info/top_level.txt
bitrix24_rest-2.0.3.dist-info/RECORD
