Metadata-Version: 2.1
Name: bitrix24-rest
Version: 2.0.3
Summary: Easy way to communicate with bitrix24 portal over REST without OAuth
Home-page: https://github.com/akopdev/bitrix24-python-rest
Author: Akop Kesheshyan
Author-email: hello@akop.dev
License: MIT
Keywords: bitrix24 api rest
Classifier: Development Status :: 5 - Production/Stable
Classifier: Intended Audience :: Developers
Classifier: License :: OSI Approved :: MIT License
Classifier: Operating System :: POSIX
Classifier: Programming Language :: Python
Classifier: Topic :: Software Development :: Libraries
License-File: LICENSE
Requires-Dist: aiohttp
Provides-Extra: dev
Requires-Dist: flake8 ; extra == 'dev'
Requires-Dist: safety ; extra == 'dev'
Requires-Dist: pydocstyle ; extra == 'dev'
Requires-Dist: black ; extra == 'dev'
Requires-Dist: isort ; extra == 'dev'
Requires-Dist: pytest ; extra == 'dev'
Requires-Dist: pytest-cov ; extra == 'dev'
Requires-Dist: pytest-asyncio ; extra == 'dev'
Requires-Dist: aioresponses ; extra == 'dev'
Requires-Dist: pytest-aiohttp ; extra == 'dev'
